keyfactor_v_1_client/__init__.py
keyfactor_v_1_client/api/__init__.py
keyfactor_v_1_client/api/agent/__init__.py
keyfactor_v_1_client/api/agent/agent_approve.py
keyfactor_v_1_client/api/agent/agent_disapprove.py
keyfactor_v_1_client/api/agent/agent_fetch_logs.py
keyfactor_v_1_client/api/agent/agent_get_agent_detail.py
keyfactor_v_1_client/api/agent/agent_get_agents.py
keyfactor_v_1_client/api/agent/agent_reset_0.py
keyfactor_v_1_client/api/agent/agent_reset_1.py
keyfactor_v_1_client/api/agent/agent_set_auth_certificate_reenrollment.py
keyfactor_v_1_client/api/agent_blueprint/__init__.py
keyfactor_v_1_client/api/agent_blueprint/agent_blueprint_apply_blueprint.py
keyfactor_v_1_client/api/agent_blueprint/agent_blueprint_delete_blueprint.py
keyfactor_v_1_client/api/agent_blueprint/agent_blueprint_generate_blueprint.py
keyfactor_v_1_client/api/agent_blueprint/agent_blueprint_get_agent_blueprint.py
keyfactor_v_1_client/api/agent_blueprint/agent_blueprint_get_agent_blueprints.py
keyfactor_v_1_client/api/agent_blueprint/agent_blueprint_get_blueprint_jobs.py
keyfactor_v_1_client/api/agent_blueprint/agent_blueprint_get_blueprint_stores.py
keyfactor_v_1_client/api/agent_pool/__init__.py
keyfactor_v_1_client/api/agent_pool/agent_pool_create_agent_pool.py
keyfactor_v_1_client/api/agent_pool/agent_pool_delete_agent_pool.py
keyfactor_v_1_client/api/agent_pool/agent_pool_get_agent_pool_by_id.py
keyfactor_v_1_client/api/agent_pool/agent_pool_get_agent_pools.py
keyfactor_v_1_client/api/agent_pool/agent_pool_get_default_agent_pool_agents.py
keyfactor_v_1_client/api/agent_pool/agent_pool_update_agent_pool.py
keyfactor_v_1_client/api/audit_log/__init__.py
keyfactor_v_1_client/api/audit_log/audit_log_download_csv.py
keyfactor_v_1_client/api/audit_log/audit_log_get_audit_log.py
keyfactor_v_1_client/api/audit_log/audit_log_get_audit_logs.py
keyfactor_v_1_client/api/audit_log/audit_log_get_related_entities.py
keyfactor_v_1_client/api/audit_log/audit_log_validate_audit_log.py
keyfactor_v_1_client-1.0.3.dist-info/WHEEL
keyfactor_v_1_client-1.0.3.dist-info/METADATA
keyfactor_v_1_client-1.0.3.dist-info/RECORD
